{
  "id": "WFCreate001",
  "name": "N8N Manager - Workflow Create",
  "description": "Creates a new n8n workflow from a JSON definition. Requires name, nodes, and connections. Returns the created workflow with its assigned ID.",
  "active": true,
  "isArchived": false,
  "nodes": [
    {
      "parameters": {
        "workflowInputs": {
          "values": [
            {
              "name": "workflowJson",
              "type": "string"
            }
          ]
        }
      },
      "type": "n8n-nodes-base.executeWorkflowTrigger",
      "typeVersion": 1.1,
      "position": [
        0,
        0
      ],
      "id": "wfcreate-trigger-001",
      "name": "When Executed by Another Workflow"
    },
    {
      "parameters": {
        "jsCode": "// Validate and prepare workflow JSON\nconst input = items[0].json;\nlet workflowDef;\n\ntry {\n  // Parse if string, use directly if object\n  workflowDef = typeof input.workflowJson === 'string' \n    ? JSON.parse(input.workflowJson) \n    : input.workflowJson;\n} catch (e) {\n  throw new Error('Invalid workflow JSON: ' + e.message);\n}\n\n// Ensure required fields\nif (!workflowDef.name) {\n  throw new Error('Workflow must have a name');\n}\nif (!workflowDef.nodes || !Array.isArray(workflowDef.nodes)) {\n  workflowDef.nodes = [];\n}\nif (!workflowDef.connections) {\n  workflowDef.connections = {};\n}\nif (!workflowDef.settings) {\n  workflowDef.settings = {};\n}\n\nreturn [{\n  json: {\n    workflowBody: JSON.stringify(workflowDef)\n  }\n}];"
      },
      "type": "n8n-nodes-base.code",
      "typeVersion": 2,
      "position": [
        220,
        0
      ],
      "id": "wfcreate-validate-001",
      "name": "Validate Workflow"
    },
    {
      "parameters": {
        "workflowId": {
          "__rl": true,
          "value": "rJoy4infFhxMynsJ",
          "mode": "id"
        },
        "workflowInputs": {
          "mappingMode": "defineBelow",
          "value": {
            "requestPath": "/workflows",
            "requestBody": "={{ $json.workflowBody }}",
            "requestMethod": "POST"
          },
          "matchingColumns": [],
          "schema": [
            {
              "id": "requestPath",
              "displayName": "requestPath",
              "required": true,
              "type": "string"
            },
            {
              "id": "requestBody",
              "displayName": "requestBody",
              "required": false,
              "type": "string"
            },
            {
              "id": "requestMethod",
              "displayName": "requestMethod",
              "required": true,
              "type": "string"
            }
          ]
        }
      },
      "type": "n8n-nodes-base.executeWorkflow",
      "typeVersion": 1.2,
      "position": [
        440,
        0
      ],
      "id": "wfcreate-api-001",
      "name": "Call N8N API"
    },
    {
      "parameters": {
        "jsCode": "// Return created workflow info\nconst response = items[0].json;\n\nreturn [{\n  json: {\n    success: true,\n    message: 'Workflow created successfully',\n    workflow: {\n      id: response.id,\n      name: response.name,\n      active: response.active,\n      createdAt: response.createdAt\n    }\n  }\n}];"
      },
      "type": "n8n-nodes-base.code",
      "typeVersion": 2,
      "position": [
        660,
        0
      ],
      "id": "wfcreate-format-001",
      "name": "Format Response"
    }
  ],
  "connections": {
    "When Executed by Another Workflow": {
      "main": [
        [
          {
            "node": "Validate Workflow",
            "type": "main",
            "index": 0
          }
        ]
      ]
    },
    "Validate Workflow": {
      "main": [
        [
          {
            "node": "Call N8N API",
            "type": "main",
            "index": 0
          }
        ]
      ]
    },
    "Call N8N API": {
      "main": [
        [
          {
            "node": "Format Response",
            "type": "main",
            "index": 0
          }
        ]
      ]
    }
  },
  "settings": {
    "executionOrder": "v1"
  },
  "staticData": null,
  "meta": {},
  "pinData": {},
  "tags": []
}

